[
  {
    "home_team": "Argentina",
    "away_team": "Austria",
    "neutral": 1,
    "lambda_home": 2.0081527274194477,
    "lambda_away": 0.7858622890393159,
    "market": {
      "p_home": 0.6586930352463313,
      "p_draw": 0.2171978379195809,
      "p_away": 0.12410912683408784,
      "overround_1x2": 0.0,
      "p_over25": 0.49139182862677105,
      "p_under25": 0.508608171373229,
      "overround_ou25": -1.1102230246251565e-16,
      "lambda_total": 2.64,
      "lambda_home": 1.9059373103910568,
      "lambda_away": 0.7340626896089432
    },
    "ml": {
      "p_home": 0.7296802574398824,
      "p_draw": 0.1801654137531036,
      "p_away": 0.09015432880701396,
      "p_over25": 0.5636474775694481,
      "p_btts_yes": 0.5022518068231259,
      "lambda_home": 2.1330826815652584,
      "lambda_away": 0.8491729105653268
    },
    "dixon_coles": {
      "p_home": 0.649952597427735,
      "p_draw": 0.2224980526191161,
      "p_away": 0.12754934995314882,
      "p_over25": 0.5291143634425087,
      "p_under25": 0.47088563655749127,
      "p_btts_yes": 0.48086580802018725,
      "p_btts_no": 0.5191341919798127
    },
    "monte_carlo": {
      "n_sim": 200000,
      "home_win": 0.651695,
      "draw": 0.221165,
      "away_win": 0.12714,
      "over25": 0.52896,
      "under25": 0.47104,
      "btts_yes": 0.48015,
      "btts_no": 0.51985,
      "avg_home_goals": 2.00959,
      "avg_away_goals": 0.783695,
      "avg_total_goals": 2.793285
    },
    "final": {
      "p_home": 0.6813534535594252,
      "p_draw": 0.20556154313619765,
      "p_away": 0.11308500330437725,
      "pick": "HOME",
      "confidence": 0.6813534535594252
    },
    "top_scores": [
      {
        "score": "2-0",
        "probability": 0.12335078714878309
      },
      {
        "score": "1-0",
        "probability": 0.11319568716317943
      },
      {
        "score": "1-1",
        "probability": 0.10619750548049463
      },
      {
        "score": "2-1",
        "probability": 0.0969367319435441
      },
      {
        "score": "3-0",
        "probability": 0.08256907321405484
      },
      {
        "score": "0-0",
        "probability": 0.070829947488463
      },
      {
        "score": "3-1",
        "probability": 0.064887920879852
      },
      {
        "score": "4-0",
        "probability": 0.041452827393825074
      },
      {
        "score": "0-1",
        "probability": 0.038421301008757944
      },
      {
        "score": "2-2",
        "probability": 0.038089461028572066
      }
    ],
    "odds": {
      "odds_home": 1.5181578466607442,
      "odds_draw": 4.604097396081159,
      "odds_away": 8.05742515082573,
      "odds_over25": 2.0350358751275337,
      "odds_under25": 1.96615008622458
    },
    "value": {
      "has_value_data": true,
      "bets": [
        {
          "market": "HOME",
          "probability": 0.6813534535594252,
          "odds": 1.5181578466607442,
          "implied_probability": 0.6586930352463313,
          "edge": 0.022660418313093955,
          "ev": 0.03440209187063825,
          "is_value": true
        },
        {
          "market": "DRAW",
          "probability": 0.20556154313619765,
          "odds": 4.604097396081159,
          "implied_probability": 0.2171978379195809,
          "edge": -0.011636294783383239,
          "ev": -0.05357463451220745,
          "is_value": false
        },
        {
          "market": "AWAY",
          "probability": 0.11308500330437725,
          "odds": 8.05742515082573,
          "implied_probability": 0.12410912683408784,
          "edge": -0.011024123529710592,
          "ev": -0.08882605019409984,
          "is_value": false
        },
        {
          "market": "OVER_2_5",
          "probability": 0.5291143634425087,
          "odds": 2.0350358751275337,
          "implied_probability": 0.491391828626771,
          "edge": 0.03772253481573773,
          "ev": 0.07676671165077376,
          "is_value": true
        },
        {
          "market": "UNDER_2_5",
          "probability": 0.47088563655749127,
          "odds": 1.96615008622458,
          "implied_probability": 0.5086081713732289,
          "edge": -0.03772253481573762,
          "ev": -0.07416816508057233,
          "is_value": false
        }
      ],
      "best_value": {
        "market": "OVER_2_5",
        "probability": 0.5291143634425087,
        "odds": 2.0350358751275337,
        "implied_probability": 0.491391828626771,
        "edge": 0.03772253481573773,
        "ev": 0.07676671165077376,
        "is_value": true
      },
      "best_edge": {
        "market": "OVER_2_5",
        "probability": 0.5291143634425087,
        "odds": 2.0350358751275337,
        "implied_probability": 0.491391828626771,
        "edge": 0.03772253481573773,
        "ev": 0.07676671165077376,
        "is_value": true
      }
    },
    "match_id": "WC2026-041",
    "date_utc": "2026-06-22T17:00:00+00:00",
    "date_local": "2026-06-22",
    "kickoff_local": "2026-06-22T13:00:00-04:00",
    "stage": "Group Stage",
    "group": "J",
    "venue": "TBD",
    "city": "TBD",
    "country": "TBD"
  },
  {
    "home_team": "France",
    "away_team": "Iraq",
    "neutral": 1,
    "lambda_home": 2.5748674573146597,
    "lambda_away": 0.7523815762855075,
    "market": {
      "p_home": 0.884128398772496,
      "p_draw": 0.08190561471766766,
      "p_away": 0.03396598650983633,
      "overround_1x2": -1.1102230246251565e-16,
      "p_over25": 0.7146926312225738,
      "p_under25": 0.2853073687774262,
      "overround_ou25": 0.0,
      "lambda_total": 3.7,
      "lambda_home": 2.963524183498263,
      "lambda_away": 0.7364758165017375
    },
    "ml": {
      "p_home": 0.7496178112088051,
      "p_draw": 0.16775187718075202,
      "p_away": 0.0826303116104429,
      "p_over25": 0.5471537034116443,
      "p_btts_yes": 0.48833523482981245,
      "lambda_home": 2.0998425697569223,
      "lambda_away": 0.7718219493545597
    },
    "dixon_coles": {
      "p_home": 0.7592287604279423,
      "p_draw": 0.16121778975430606,
      "p_away": 0.07955344981775134,
      "p_over25": 0.6459883185613331,
      "p_under25": 0.3540116814386669,
      "p_btts_yes": 0.4954354572958644,
      "p_btts_no": 0.5045645427041356
    },
    "monte_carlo": {
      "n_sim": 200000,
      "home_win": 0.759025,
      "draw": 0.162075,
      "away_win": 0.0789,
      "over25": 0.6471,
      "under25": 0.3529,
      "btts_yes": 0.49616,
      "btts_no": 0.50384,
      "avg_home_goals": 2.574635,
      "avg_away_goals": 0.753845,
      "avg_total_goals": 3.32848
    },
    "final": {
      "p_home": 0.805824783539066,
      "p_draw": 0.1317798503389068,
      "p_away": 0.062395366122027396,
      "pick": "HOME",
      "confidence": 0.805824783539066
    },
    "top_scores": [
      {
        "score": "2-0",
        "probability": 0.11898945734581957
      },
      {
        "score": "3-0",
        "probability": 0.10212736049442722
      },
      {
        "score": "2-1",
        "probability": 0.08952547547920488
      },
      {
        "score": "1-0",
        "probability": 0.08546996039373386
      },
      {
        "score": "3-1",
        "probability": 0.07683874447067542
      },
      {
        "score": "1-1",
        "probability": 0.07649172212524565
      },
      {
        "score": "4-0",
        "probability": 0.06574110425963585
      },
      {
        "score": "4-1",
        "probability": 0.049462395649614715
      },
      {
        "score": "0-0",
        "probability": 0.042848360251177414
      },
      {
        "score": "5-0",
        "probability": 0.033854925993213304
      }
    ],
    "odds": {
      "odds_home": 1.131057436214443,
      "odds_draw": 12.209175200589668,
      "odds_away": 29.441217604864992,
      "odds_over25": 1.3992028969004078,
      "odds_under25": 3.504991841904088
    },
    "value": {
      "has_value_data": true,
      "bets": [
        {
          "market": "HOME",
          "probability": 0.805824783539066,
          "odds": 1.131057436214443,
          "implied_probability": 0.8841283987724959,
          "edge": -0.07830361523342999,
          "ev": -0.0885658862922456,
          "is_value": false
        },
        {
          "market": "DRAW",
          "probability": 0.1317798503389068,
          "odds": 12.209175200589668,
          "implied_probability": 0.08190561471766765,
          "edge": 0.049874235621239146,
          "ev": 0.6089232806951987,
          "is_value": true
        },
        {
          "market": "AWAY",
          "probability": 0.062395366122027396,
          "odds": 29.441217604864992,
          "implied_probability": 0.03396598650983632,
          "edge": 0.028429379612191073,
          "ev": 0.8369955515338297,
          "is_value": true
        },
        {
          "market": "OVER_2_5",
          "probability": 0.6459883185613331,
          "odds": 1.3992028969004078,
          "implied_probability": 0.7146926312225738,
          "edge": -0.06870431266124066,
          "ev": -0.09613127330515925,
          "is_value": false
        },
        {
          "market": "UNDER_2_5",
          "probability": 0.3540116814386669,
          "odds": 3.504991841904088,
          "implied_probability": 0.2853073687774262,
          "edge": 0.06870431266124072,
          "ev": 0.24080805538127636,
          "is_value": true
        }
      ],
      "best_value": {
        "market": "AWAY",
        "probability": 0.062395366122027396,
        "odds": 29.441217604864992,
        "implied_probability": 0.03396598650983632,
        "edge": 0.028429379612191073,
        "ev": 0.8369955515338297,
        "is_value": true
      },
      "best_edge": {
        "market": "UNDER_2_5",
        "probability": 0.3540116814386669,
        "odds": 3.504991841904088,
        "implied_probability": 0.2853073687774262,
        "edge": 0.06870431266124072,
        "ev": 0.24080805538127636,
        "is_value": true
      }
    },
    "match_id": "WC2026-042",
    "date_utc": "2026-06-22T21:00:00+00:00",
    "date_local": "2026-06-22",
    "kickoff_local": "2026-06-22T17:00:00-04:00",
    "stage": "Group Stage",
    "group": "I",
    "venue": "TBD",
    "city": "TBD",
    "country": "TBD"
  },
  {
    "home_team": "Norway",
    "away_team": "Senegal",
    "neutral": 1,
    "lambda_home": 1.3213058030803513,
    "lambda_away": 1.298977955156132,
    "market": null,
    "ml": {
      "p_home": 0.4101653961296889,
      "p_draw": 0.24905647828131347,
      "p_away": 0.3407781255889976,
      "p_over25": 0.5296607600025781,
      "p_btts_yes": 0.6156499307928117,
      "lambda_home": 1.3213058030803513,
      "lambda_away": 1.298977955156132
    },
    "dixon_coles": {
      "p_home": 0.36137086009538166,
      "p_draw": 0.28768463815868334,
      "p_away": 0.35094450174593494,
      "p_over25": 0.48665039982965663,
      "p_under25": 0.5133496001703434,
      "p_btts_yes": 0.5456769271281726,
      "p_btts_no": 0.4543230728718274
    },
    "monte_carlo": {
      "n_sim": 200000,
      "home_win": 0.360325,
      "draw": 0.28773,
      "away_win": 0.351945,
      "over25": 0.48714,
      "under25": 0.51286,
      "btts_yes": 0.54525,
      "btts_no": 0.45475,
      "avg_home_goals": 1.320865,
      "avg_away_goals": 1.301605,
      "avg_total_goals": 2.62247
    },
    "final": {
      "p_home": 0.3882078549142507,
      "p_draw": 0.2664391502261299,
      "p_away": 0.34535299485961946,
      "pick": "HOME",
      "confidence": 0.3882078549142507
    },
    "top_scores": [
      {
        "score": "1-1",
        "probability": 0.1374115251625917
      },
      {
        "score": "0-0",
        "probability": 0.08527418578053635
      },
      {
        "score": "1-0",
        "probability": 0.08367562463658866
      },
      {
        "score": "2-1",
        "probability": 0.0825284752761155
      },
      {
        "score": "0-1",
        "probability": 0.08205055409706154
      },
      {
        "score": "1-2",
        "probability": 0.08113388271390397
      },
      {
        "score": "2-0",
        "probability": 0.06353339173196046
      },
      {
        "score": "0-2",
        "probability": 0.06140431876160469
      },
      {
        "score": "2-2",
        "probability": 0.05360133502816096
      },
      {
        "score": "3-1",
        "probability": 0.03634845110056823
      }
    ],
    "odds": null,
    "value": {
      "has_value_data": false,
      "bets": [],
      "best_value": null,
      "best_edge": null
    },
    "match_id": "WC2026-043",
    "date_utc": "2026-06-23T00:00:00+00:00",
    "date_local": "2026-06-22",
    "kickoff_local": "2026-06-22T20:00:00-04:00",
    "stage": "Group Stage",
    "group": "I",
    "venue": "TBD",
    "city": "TBD",
    "country": "TBD"
  },
  {
    "home_team": "Jordan",
    "away_team": "Algeria",
    "neutral": 1,
    "lambda_home": 0.9914804884619522,
    "lambda_away": 1.6048801718401908,
    "market": null,
    "ml": {
      "p_home": 0.20606557816500595,
      "p_draw": 0.33247943795270385,
      "p_away": 0.46145498388229006,
      "p_over25": 0.4453798972702545,
      "p_btts_yes": 0.5463388758601085,
      "lambda_home": 0.9914804884619522,
      "lambda_away": 1.6048801718401908
    },
    "dixon_coles": {
      "p_home": 0.22183655006651645,
      "p_draw": 0.27329614440584443,
      "p_away": 0.5048673055276391,
      "p_over25": 0.4806558512021983,
      "p_under25": 0.5193441487978017,
      "p_btts_yes": 0.5144651987322882,
      "p_btts_no": 0.48553480126771176
    },
    "monte_carlo": {
      "n_sim": 200000,
      "home_win": 0.222225,
      "draw": 0.272865,
      "away_win": 0.50491,
      "over25": 0.47938,
      "under25": 0.52062,
      "btts_yes": 0.51446,
      "btts_no": 0.48554,
      "avg_home_goals": 0.99206,
      "avg_away_goals": 1.602945,
      "avg_total_goals": 2.595005
    },
    "final": {
      "p_home": 0.21316251552068569,
      "p_draw": 0.30584695585661714,
      "p_away": 0.4809905286226972,
      "pick": "AWAY",
      "confidence": 0.4809905286226972
    },
    "top_scores": [
      {
        "score": "1-1",
        "probability": 0.13047725851594869
      },
      {
        "score": "0-1",
        "probability": 0.10777335169076148
      },
      {
        "score": "0-2",
        "probability": 0.09599985600282733
      },
      {
        "score": "1-2",
        "probability": 0.09518198412196031
      },
      {
        "score": "0-0",
        "probability": 0.08640602576087988
      },
      {
        "score": "1-0",
        "probability": 0.0620478054890425
      },
      {
        "score": "2-1",
        "probability": 0.05880257091207691
      },
      {
        "score": "0-3",
        "probability": 0.05135608846615037
      },
      {
        "score": "1-3",
        "probability": 0.050918559677914
      },
      {
        "score": "2-2",
        "probability": 0.0471855400550095
      }
    ],
    "odds": null,
    "value": {
      "has_value_data": false,
      "bets": [],
      "best_value": null,
      "best_edge": null
    },
    "match_id": "WC2026-044",
    "date_utc": "2026-06-23T03:00:00+00:00",
    "date_local": "2026-06-22",
    "kickoff_local": "2026-06-22T23:00:00-04:00",
    "stage": "Group Stage",
    "group": "J",
    "venue": "TBD",
    "city": "TBD",
    "country": "TBD"
  }
]